gym_minatar/__init__.py
gym_minatar/envs/__init__.py
gym_minatar/envs/asterix.py
gym_minatar/envs/base.py
gym_minatar/envs/breakout.py
gym_minatar/envs/freeway.py
gym_minatar/envs/seaquest.py
gym_minatar/envs/space_invaders.py
gym_pygame/__init__.py
gym_pygame/envs/__init__.py
gym_pygame/envs/base.py
gym_pygame/envs/catcher.py
gym_pygame/envs/flappybird.py
gym_pygame/envs/pixelcopter.py
gym_pygame/envs/pong.py
gym_pygame/envs/puckworld.py
gym_games-1.0.3.dist-info/LICENSE
gym_games-1.0.3.dist-info/METADATA
gym_games-1.0.3.dist-info/WHEEL
gym_games-1.0.3.dist-info/dependency_links.txt
gym_games-1.0.3.dist-info/top_level.txt
gym_games-1.0.3.dist-info/RECORD
