Metadata-Version: 2.1
Name: gym-games
Version: 1.0.3
Summary: This is a gym version of various games for reinforcenment learning.
Home-page: https://github.com/qlan3/gym-games
Author: qlan3
Author-email: qlan3@ualberta.ca
License: MIT
Keywords: AI,Reinforcement Learning,Games,Pygame,MinAtar
Platform: UNKNOWN
Requires-Python: >=3.5
Requires-Dist: numpy (>=1.16.4)
Requires-Dist: MinAtar (>=1.0.4)
Requires-Dist: gym (>=0.13.0)
Requires-Dist: setuptools (>=41.0.1)
Requires-Dist: pygame (>=1.9.6)
Requires-Dist: ple (>=0.0.1)
